fluen/__init__.py
fluen/cli.py
fluen/config.py
fluen/llm_factory.py
fluen/orchestrator.py
fluen/analyzer/__init__.py
fluen/analyzer/file_analyzer.py
fluen/analyzer/manifest_enricher.py
fluen/analyzer/project_analyzer.py
fluen/generator/__init__.py
fluen/generator/cross_referencer.py
fluen/generator/doc_generator.py
fluen/generator/manifest.py
fluen/generator/templates/.DS_Store
fluen/generator/templates/template_manager.py
fluen/generator/templates/__pycache__/template_manager.cpython-310.pyc
fluen/generator/templates/default/.DS_Store
fluen/generator/templates/default/html/empty.html
fluen/generator/templates/default/html/index.html
fluen/generator/templates/default/html/reference.html
fluen/generator/templates/default/md/readme.md
fluen/generator/templates/default/md/reference.md
fluen/generator/templates/default/md/summary.md
fluen/generator/templates/default/static/logo-placeholder.png
fluen/generator/templates/default/static/script.js
fluen/generator/templates/default/static/styles.css
fluen/git_integration/__init__.py
fluen/git_integration/manager.py
fluen/llm_providers/__init__.py
fluen/llm_providers/base_provider.py
fluen/llm_providers/mistral_ai_provider.py
fluen/llm_providers/ollama_provider.py
fluen/llm_providers/openai_provider.py
fluen/models/__init__.py
fluen/models/scan.py
fluen/state/__init__.py
fluen/state/manager.py
fluen/tests/__init__.py
fluen/tests/conftest.py
fluen/tests/test_file_analyzer.py
fluen/tests/test_git_manager.py
fluen-0.1.41.dist-info/LICENSE
fluen-0.1.41.dist-info/METADATA
fluen-0.1.41.dist-info/WHEEL
fluen-0.1.41.dist-info/entry_points.txt
fluen-0.1.41.dist-info/top_level.txt
fluen-0.1.41.dist-info/RECORD
