Metadata-Version: 2.1
Name: fluen
Version: 0.1.41
Summary: LLM-based AI powered Code Documentation Generator
Home-page: https://github.com/Fluen-io/fluen-core
Author: Abi Chatterjee
Author-email: abi@fluen.io
Keywords: documentation,llm,code-analysis
Classifier: Development Status :: 3 - Alpha
Classifier: Intended Audience :: Developers
Classifier: Topic :: Software Development :: Documentation
Classifier: Programming Language :: Python :: 3
Classifier: Programming Language :: Python :: 3.8
Classifier: Programming Language :: Python :: 3.9
Classifier: Programming Language :: Python :: 3.10
Classifier: Programming Language :: Python :: 3.11
Requires-Python: >=3.8
License-File: LICENSE
Requires-Dist: click>=8.0.0
Requires-Dist: gitpython>=3.1.0
Requires-Dist: pyyaml>=6.0
Requires-Dist: rich>=10.0.0
Requires-Dist: jinja2>=3.0.0
Requires-Dist: aiohttp>=3.8.0
Requires-Dist: openai>=1.0.0
Requires-Dist: mistralai>=0.0.7
Requires-Dist: markdown>=3.5.0
Requires-Dist: bleach>=6.1.0
Provides-Extra: dev
Requires-Dist: pytest>=7.0.0; extra == "dev"
Requires-Dist: pytest-asyncio>=0.21.0; extra == "dev"
Requires-Dist: pytest-cov>=4.0.0; extra == "dev"
Requires-Dist: black>=23.0.0; extra == "dev"
Requires-Dist: mypy>=1.0.0; extra == "dev"
Requires-Dist: flake8>=6.0.0; extra == "dev"
